pintor_pca/__init__.py
pintor_pca/core.py
pintor_pintor_pca-1.0.0.dist-info/METADATA
pintor_pintor_pca-1.0.0.dist-info/WHEEL
pintor_pintor_pca-1.0.0.dist-info/top_level.txt
pintor_pintor_pca-1.0.0.dist-info/RECORD
