Metadata-Version: 2.4
Name: pintor-pintor-pca
Version: 1.0.0
Summary: Biblioteca para aplicar o método de PCA
Home-page: https://github.com/PedroPintor/pintor-pintor-pca.git
Author: Pedro
Classifier: Programming Language :: Python :: 3
Classifier: License :: OSI Approved :: MIT License
Classifier: Operating System :: OS Independent
Requires-Python: >=3.7
Requires-Dist: pandas>=1.3.0
Requires-Dist: numpy>=1.20.0
Requires-Dist: factor-analyzer>=0.4.0
Dynamic: author
Dynamic: classifier
Dynamic: home-page
Dynamic: requires-dist
Dynamic: requires-python
Dynamic: summary
